grale/__init__.py
grale/core.py
grale-1.0.1.dist-info/licenses/LICENSE
grale-1.0.1.dist-info/METADATA
grale-1.0.1.dist-info/WHEEL
grale-1.0.1.dist-info/top_level.txt
grale-1.0.1.dist-info/RECORD
