Metadata-Version: 2.4
Name: grale
Version: 1.0.1
Summary: Tools for gravitational lensing and GW event analysis
Author-email: Shannon Schroeder <a12023808@unet.univie.ac.at>
License: MIT
Project-URL: Homepage, https://github.com/ShannonS00/GRaLE
Requires-Python: >=3.8
License-File: LICENSE
Requires-Dist: numpy>=1.21
Requires-Dist: astropy>=5.0
Requires-Dist: scipy>=1.7
Requires-Dist: matplotlib>=3.4
Dynamic: license-file
